flask_mdict/__init__.py
flask_mdict/dbdict_query.py
flask_mdict/forms.py
flask_mdict/helper.py
flask_mdict/mdict_query2.py
flask_mdict/utils.py
flask_mdict/views.py
flask_mdict/plugins/__init__.py
flask_mdict/plugins/alibaba.py
flask_mdict/plugins/bing.py
flask_mdict/plugins/google.py
flask_mdict/plugins/iciba.py
flask_mdict/plugins/volcengine.py
flask_mdict/plugins/youdao.py
flask_mdict/plugins/__pycache__/__init__.cpython-310.pyc
flask_mdict/plugins/__pycache__/__init__.cpython-313.pyc
flask_mdict/plugins/__pycache__/alibaba.cpython-310.pyc
flask_mdict/plugins/__pycache__/alibaba.cpython-313.pyc
flask_mdict/plugins/__pycache__/bing.cpython-310.pyc
flask_mdict/plugins/__pycache__/bing.cpython-313.pyc
flask_mdict/plugins/__pycache__/google.cpython-310.pyc
flask_mdict/plugins/__pycache__/google.cpython-313.pyc
flask_mdict/plugins/__pycache__/iciba.cpython-310.pyc
flask_mdict/plugins/__pycache__/iciba.cpython-313.pyc
flask_mdict/plugins/__pycache__/volcengine.cpython-310.pyc
flask_mdict/plugins/__pycache__/volcengine.cpython-313.pyc
flask_mdict/plugins/__pycache__/youdao.cpython-310.pyc
flask_mdict/plugins/__pycache__/youdao.cpython-313.pyc
flask_mdict/plugins/static/alibaba.ico
flask_mdict/plugins/static/bing.svg
flask_mdict/plugins/static/google_translate-130x130.png
flask_mdict/plugins/static/google_translate.ico
flask_mdict/plugins/static/iciba.ico
flask_mdict/plugins/static/volcengine.png
flask_mdict/plugins/static/youdao.png
flask_mdict/static/Ox3000_Rect1_mod_web.png
flask_mdict/static/favicon.ico
flask_mdict/static/google_translate-130x130.png
flask_mdict/static/google_translate.ico
flask_mdict/static/logo.ico
flask_mdict/static/mdict-255x255.png
flask_mdict/static/mdict-44x44.png
flask_mdict/static/bootstrap-4.5.0/css/bootstrap-grid.css
flask_mdict/static/bootstrap-4.5.0/css/bootstrap-grid.css.map
flask_mdict/static/bootstrap-4.5.0/css/bootstrap-grid.min.css
flask_mdict/static/bootstrap-4.5.0/css/bootstrap-grid.min.css.map
flask_mdict-1.4.21.dist-info/licenses/LICENSE
flask_mdict-1.4.21.dist-info/licenses/LICENSE.996ICU
flask_mdict-1.4.21.dist-info/METADATA
flask_mdict-1.4.21.dist-info/WHEEL
flask_mdict-1.4.21.dist-info/top_level.txt
flask_mdict-1.4.21.dist-info/RECORD
