Metadata-Version: 2.4
Name: flask_mdict
Version: 1.4.21
Summary: Flask Mdict Server
Home-page: https://github.com/liuyug/flask-mdict
Author: Yugang LIU
Author-email: liuyug@gmail.com
License: MIT
Platform: noarch
Requires-Python: >=3.6
License-File: LICENSE
License-File: LICENSE.996ICU
Requires-Dist: Flask
Requires-Dist: Flask-WTF
Requires-Dist: WTForms-Components
Requires-Dist: translators
Dynamic: author
Dynamic: author-email
Dynamic: description
Dynamic: description-content-type
Dynamic: home-page
Dynamic: license
Dynamic: license-file
Dynamic: platform
Dynamic: requires-dist
Dynamic: requires-python
Dynamic: summary
